selectionfunctions/__init__.py
selectionfunctions/befl_2019.py
selectionfunctions/cog_ii.py
selectionfunctions/config.py
selectionfunctions/equirectangular_map.py
selectionfunctions/fetch_utils.py
selectionfunctions/healpix_map.py
selectionfunctions/json_serializers.py
selectionfunctions/map.py
selectionfunctions/sfexceptions.py
selectionfunctions/source.py
selectionfunctions/std_paths.py
selectionfunctions/unstructured_map.py
selectionfunctions-0.2.0.dist-info/LICENSE.txt
selectionfunctions-0.2.0.dist-info/METADATA
selectionfunctions-0.2.0.dist-info/WHEEL
selectionfunctions-0.2.0.dist-info/top_level.txt
selectionfunctions-0.2.0.dist-info/RECORD
