Metadata-Version: 2.1
Name: selectionfunctions
Version: 0.2.0
Summary: Uniform interface for the selection functions of astronomical surveys.
Home-page: https://github.com/gaiaverse/selectionfunctions
Author: Douglas Boubert
Author-email: douglasboubert@gmail.com
License: GPLv2
Download-URL: https://github.com/gaiaverse/selectionfunctions/archive/v0.2.0.tar.gz
Platform: UNKNOWN
Requires-Dist: numpy
Requires-Dist: scipy
Requires-Dist: astropy
Requires-Dist: h5py
Requires-Dist: healpy
Requires-Dist: requests
Requires-Dist: progressbar2
Requires-Dist: six
